mitmproxy_addon_launcher.py
mitmproxy_addon_launcher-0.1.2.dist-info/METADATA
mitmproxy_addon_launcher-0.1.2.dist-info/WHEEL
mitmproxy_addon_launcher-0.1.2.dist-info/entry_points.txt
mitmproxy_addon_launcher-0.1.2.dist-info/licenses/LICENSE
mitmproxy_addon_launcher-0.1.2.dist-info/RECORD
