Metadata-Version: 2.4
Name: mitmproxy-addon-launcher
Version: 0.1.2
Summary: Load mitmproxy/mitmweb addons from entry points
Project-URL: github, https://github.com/davidszotten/mitmproxy-addon-launcher
License-File: LICENSE
Requires-Python: >=3.10
Requires-Dist: mitmproxy
